setup.py
oauth_cli/__init__.py
oauth_cli/__main__.py
oauth_cli/config.py
oauth_cli.egg-info/PKG-INFO
oauth_cli.egg-info/SOURCES.txt
oauth_cli.egg-info/dependency_links.txt
oauth_cli.egg-info/entry_points.txt
oauth_cli.egg-info/not-zip-safe
oauth_cli.egg-info/requires.txt
oauth_cli.egg-info/top_level.txt
oauth_cli/aws/__init__.py
oauth_cli/aws/aws_account.py
oauth_cli/aws/aws_console.py
oauth_cli/aws/aws_saml_assertion.py
oauth_cli/aws/aws_sts_command.py
oauth_cli/pkce/__init__.py
oauth_cli/pkce/callback.py
oauth_cli/pkce/command.py
oauth_cli/saml/__init__.py
oauth_cli/saml/callback.py
oauth_cli/saml/command.py
oauth_cli/util/__init__.py
oauth_cli/util/url.py